main.py
simplemarkdownsplitter/__init__.py
simplemarkdownsplitter/split.py
simple_markdown_splitter-0.4.dist-info/LICENSE
simple_markdown_splitter-0.4.dist-info/METADATA
simple_markdown_splitter-0.4.dist-info/WHEEL
simple_markdown_splitter-0.4.dist-info/top_level.txt
simple_markdown_splitter-0.4.dist-info/RECORD
