Metadata-Version: 2.1
Name: simple-markdown-splitter
Version: 0.4
Summary: A simple markdown splitter
Author-email: Electronic Mango <78230210+Electronic-Mango@users.noreply.github.com>
License: MIT License
Project-URL: Homepage, https://github.com/Electronic-Mango/simple-markdown-splitter
Project-URL: Documentation, https://electronic-mango.github.io/simple-markdown-splitter
Project-URL: Repository, https://github.com/Electronic-Mango/simple-markdown-splitter
Keywords: markdown,splitter,split
Classifier: Development Status :: 3 - Alpha
Classifier: Intended Audience :: Developers
Classifier: Topic :: Software Development :: Build Tools
Classifier: License :: OSI Approved :: MIT License
Classifier: Programming Language :: Python :: 3
Classifier: Programming Language :: Python :: 3.11
Requires-Python: >=3.11
License-File: LICENSE
